{
  "_fv": 28,
  "_type": "recipe",
  "definition": {
    "recipeType": "Crafting",
    "xpReward": 0.0,
    "cookingTime": 200,
    "recipeRetstackSize": 1,
    "group": "",
    "recipeShapeless": false,
    "recipeSlots": [
      {
        "value": "Items.GOLD_INGOT"
      },
      {
        "value": "Items.GOLD_INGOT"
      },
      {
        "value": "Items.GOLD_INGOT"
      },
      {
        "value": "Items.GOLD_INGOT"
      },
      {
        "value": "Items.APPLE"
      },
      {
        "value": "Items.GOLD_INGOT"
      },
      {
        "value": "Items.GOLD_INGOT"
      },
      {
        "value": "Items.GOLD_INGOT"
      },
      {
        "value": "Items.GOLD_INGOT"
      }
    ],
    "recipeReturnStack": {
      "value": "CUSTOM:Corruption"
    },
    "name": "golden_apple_overide",
    "namespace": "minecraft"
  }
}